dataprocessor_vb/__init__.py
dataprocessor_vb/audio_processor.py
dataprocessor_vb/categorical_processor.py
dataprocessor_vb/config.py
dataprocessor_vb/data_cleaner.py
dataprocessor_vb/data_loader.py
dataprocessor_vb/evaluator.py
dataprocessor_vb/feature_engineer.py
dataprocessor_vb/image_augmenter.py
dataprocessor_vb/image_processor.py
dataprocessor_vb/outlier_handler.py
dataprocessor_vb/pipeline.py
dataprocessor_vb/scaling.py
dataprocessor_vb/text_processor.py
dataprocessor_vb/time_series_processor.py
dataprocessor_vb-0.1.1.dist-info/METADATA
dataprocessor_vb-0.1.1.dist-info/WHEEL
dataprocessor_vb-0.1.1.dist-info/RECORD
