Metadata-Version: 2.1
Name: dataprocessor_vb
Version: 0.1.1
Summary: A comprehensive data processing library.
Keywords: data,processing,cleaning,visualization,feature engineering
Author: Vicba
Author-email: victor.barra@live.be
Requires-Python: >=3.12,<4.0
Classifier: License :: OSI Approved :: MIT License
Classifier: Operating System :: OS Independent
Classifier: Programming Language :: Python :: 3
Classifier: Programming Language :: Python :: 3.12
Classifier: Programming Language :: Python :: 3.13
Requires-Dist: albumentations (>=1.4.18,<2.0.0)
Requires-Dist: imgaug (>=0.4.0,<0.5.0)
Requires-Dist: matplotlib (>=3.9.2,<4.0.0)
Requires-Dist: nltk (>=3.9.1,<4.0.0)
Requires-Dist: numpy (>=2.1.2,<3.0.0)
Requires-Dist: pandas (>=2.2.3,<3.0.0)
Requires-Dist: pillow (>=11.0.0,<12.0.0)
Requires-Dist: scikit-learn (>=1.5.2,<2.0.0)
Project-URL: repository, https://github.com/Vicba/data-preprocessing-package
